gistim/__init__.py
gistim/__main__.py
gistim/data_extraction.py
gistim/elements.py
gistim/intersection.py
gistim/rio_utils.py
gistim/tim_server.py
gistim-0.1.dist-info/LICENSE
gistim-0.1.dist-info/METADATA
gistim-0.1.dist-info/WHEEL
gistim-0.1.dist-info/top_level.txt
gistim-0.1.dist-info/RECORD
