Metadata-Version: 2.1
Name: gistim
Version: 0.1
Summary: GIS utilities for Tim(ML) Analytic Element modeling
Home-page: https://gitlab.com/deltares/imod/qgis-tim
Author: Huite Bootsma
Author-email: huitebootsma@gmail.com
License: MIT
Keywords: groundwater modeling
Platform: UNKNOWN
Classifier: Development Status :: 3 - Alpha
Classifier: Intended Audience :: Developers
Classifier: Intended Audience :: Science/Research
Classifier: Topic :: Scientific/Engineering :: Hydrology
Classifier: License :: OSI Approved :: MIT License
Classifier: Programming Language :: Python :: 3
Classifier: Programming Language :: Python :: 3.6
Classifier: Programming Language :: Python :: 3.7
Classifier: Programming Language :: Python :: Implementation :: CPython
Requires-Python: >=3.6
Requires-Dist: affine
Requires-Dist: geopandas
Requires-Dist: matplotlib
Requires-Dist: numba
Requires-Dist: numpy
Requires-Dist: pandas
Requires-Dist: scipy
Requires-Dist: timml
Requires-Dist: xarray (>=0.15)
Provides-Extra: dev
Requires-Dist: black ; extra == 'dev'
Requires-Dist: nbstripout ; extra == 'dev'
Requires-Dist: pytest ; extra == 'dev'
Requires-Dist: pytest-cov ; extra == 'dev'
Requires-Dist: pytest-benchmark ; extra == 'dev'
Requires-Dist: sphinx ; extra == 'dev'
Requires-Dist: sphinx-rtd-theme ; extra == 'dev'
Provides-Extra: optional
Requires-Dist: rasterio (>=1) ; extra == 'optional'
Requires-Dist: netCDF4 ; extra == 'optional'
